st_btn_group/__init__.py
st_btn_group/frontend/build/asset-manifest.json
st_btn_group/frontend/build/bootstrap.min.css
st_btn_group/frontend/build/index.html
st_btn_group/frontend/build/precache-manifest.07f06846523900d2ab60f2e7cc851a9b.js
st_btn_group/frontend/build/precache-manifest.0c89546d64cfab9d7def0c81d0d31221.js
st_btn_group/frontend/build/precache-manifest.29efeb7700cc37da6cf9cd95df351bab.js
st_btn_group/frontend/build/precache-manifest.404c81a03c36cffbe71cae629aa71edb.js
st_btn_group/frontend/build/precache-manifest.546bacba5aeb05974c1cfd20f4ce0849.js
st_btn_group/frontend/build/precache-manifest.62164394aa10973a91714ebc0246d024.js
st_btn_group/frontend/build/precache-manifest.8585c1d34ba3d36cbeb4000a453bc25e.js
st_btn_group/frontend/build/precache-manifest.9bc8b4ba077d133716d04e8e617df6d0.js
st_btn_group/frontend/build/precache-manifest.f78a46a46fb1beef94e9ff843da2de8d.js
st_btn_group/frontend/build/service-worker.js
st_btn_group/frontend/build/static/js/2.8362967c.chunk.js
st_btn_group/frontend/build/static/js/2.8362967c.chunk.js.LICENSE.txt
st_btn_group/frontend/build/static/js/2.8362967c.chunk.js.map
st_btn_group/frontend/build/static/js/2.9d8196d8.chunk.js
st_btn_group/frontend/build/static/js/2.9d8196d8.chunk.js.LICENSE.txt
st_btn_group/frontend/build/static/js/2.9d8196d8.chunk.js.map
st_btn_group/frontend/build/static/js/main.433133e3.chunk.js
st_btn_group/frontend/build/static/js/main.433133e3.chunk.js.map
st_btn_group/frontend/build/static/js/main.44141d0d.chunk.js
st_btn_group/frontend/build/static/js/main.44141d0d.chunk.js.map
st_btn_group/frontend/build/static/js/main.6b3ab739.chunk.js
st_btn_group/frontend/build/static/js/main.6b3ab739.chunk.js.map
st_btn_group/frontend/build/static/js/main.7ca433ed.chunk.js
st_btn_group/frontend/build/static/js/main.7ca433ed.chunk.js.map
st_btn_group/frontend/build/static/js/main.875c4a3c.chunk.js
st_btn_group/frontend/build/static/js/main.875c4a3c.chunk.js.map
st_btn_group-0.0.11.dist-info/LICENSE
st_btn_group-0.0.11.dist-info/METADATA
st_btn_group-0.0.11.dist-info/WHEEL
st_btn_group-0.0.11.dist-info/top_level.txt
st_btn_group-0.0.11.dist-info/RECORD
